guc/__init__.py
guc/colors.py
guc/linalg.py
guc-0.0.1.dist-info/METADATA
guc-0.0.1.dist-info/WHEEL
guc-0.0.1.dist-info/licenses/LICENSE
guc-0.0.1.dist-info/RECORD
